loggly/__init__.py
loggly_api-0.3.2.dist-info/LICENSE.txt
loggly_api-0.3.2.dist-info/METADATA
loggly_api-0.3.2.dist-info/WHEEL
loggly_api-0.3.2.dist-info/top_level.txt
loggly_api-0.3.2.dist-info/RECORD
