Metadata-Version: 2.1
Name: loggly-api
Version: 0.3.2
Summary: A Python library to work with Loggly's APIs
Home-page: https://github.com/ryanjjung/loggly-api
Author: Ryan Jung
Author-email: ryanjjung@gmail.com
License: Apache License 2.0
Platform: UNKNOWN
Requires-Dist: requests
